<!DOCTYPE ui:UiBinder SYSTEM "http://dl.google.com/gwt/DTD/xhtml.ent">
<ui:UiBinder xmlns:ui="urn:ui:com.google.gwt.uibinder"
	ui:generateFormat="com.google.gwt.i18n.rebind.format.PropertiesFormat"
    ui:generateKeys="com.google.gwt.i18n.rebind.keygen.MD5KeyGenerator"
    ui:generateLocales="default"
	xmlns:wnd="urn:import:com.nabla.wapp.client.ui"
	xmlns:form="urn:import:com.nabla.wapp.client.ui.form">
	
	<ui:with field="model" type="com.nabla.dc.client.model.company.settings.ChangeLogoModel"/>

	<wnd:ModalDialog caption="Change Company Logo" icon="logo_small.png" autoClose="true">
		<ui:attribute name="caption" description="change company logo caption"/>
		<form:Form ui:field="form" model="{model}" autoFetchData="true">
			<form:TextEditBox name="{model.fields.companyName}" disabled="true" width="300"><ui:msg>Company</ui:msg></form:TextEditBox>
 			<form:UploadEditBox ui:field="logoFile" width="300" name="{model.fields.logoFile}" validFileExtensions="png,gif" maximumFiles="1"><ui:msg>Logo</ui:msg></form:UploadEditBox>
			<form:ButtonBar>
				<wnd:SubmitButton><ui:msg>*OK</ui:msg></wnd:SubmitButton>
				<wnd:CancelButton><ui:msg>*Cancel</ui:msg></wnd:CancelButton>
			</form:ButtonBar>
		</form:Form>
	</wnd:ModalDialog>
</ui:UiBinder> 